dagsim/Graph.py
dagsim/Missing.py
dagsim/Node.py
dagsim/Selection.py
dagsim/Stratify.py
dagsim/__init__.py
dagsim/base.py
dagsim/utils/__init__.py
dagsim/utils/_misc.py
dagsim/utils/helper.py
dagsim/utils/parser.py
dagsim/utils/processPlates.py
dagsim/utils/quickstart.py
dagsim-1.0.10.dist-info/licenses/LICENSE
dagsim-1.0.10.dist-info/METADATA
dagsim-1.0.10.dist-info/WHEEL
dagsim-1.0.10.dist-info/entry_points.txt
dagsim-1.0.10.dist-info/top_level.txt
dagsim-1.0.10.dist-info/RECORD
