Metadata-Version: 2.4
Name: dagsim
Version: 1.0.10
Summary: A framework and specification language for simulating data based on user-defined graphical models
Home-page: https://github.com/uio-bmi/dagsim
Author: Ghadi S. Al Hajj
Author-email: ghadia@uio.no
License: AGPL-3.0 License
Classifier: Programming Language :: Python :: 3
Classifier: License :: OSI Approved :: GNU Affero General Public License v3
Classifier: Operating System :: OS Independent
License-File: LICENSE
Requires-Dist: graphviz>=0.16
Requires-Dist: numpy>=1.20.2
Requires-Dist: pandas>=1.2.4
Requires-Dist: igraph>=0.9.6
Requires-Dist: pyyaml
Requires-Dist: ipython>=7.27.0
Dynamic: author
Dynamic: author-email
Dynamic: classifier
Dynamic: description
Dynamic: description-content-type
Dynamic: home-page
Dynamic: license
Dynamic: license-file
Dynamic: requires-dist
Dynamic: summary
